<?xml version="1.0" encoding="ISO-8859-1"?>
<!--                                                                -->
<!--   W4F: Copyright Arnaud Sahuguet and Fabien Azavant, 1998-99   -->
<!--   URL: http://db.cis.upenn.edu/W4F                             -->
<!--                                                                -->
<!DOCTYPE W4F_DOC  SYSTEM "movies.dtd">
<W4F_DOC>
  <Movie>
    <Title>Pi</Title>
    <Year>1998</Year>
    <Directed_By>
      <Director>Darren Aronofsky</Director>
    </Directed_By>
    <Genres>
      <Genre>Thriller</Genre>
      <Genre>(more)</Genre>
    </Genres>
    <Cast>
      <Actor>
        <FirstName>Sean</FirstName>
        <LastName>Gullette</LastName>
      </Actor>
      <Actor>
        <FirstName>Mark</FirstName>
        <LastName>Margolis</LastName>
      </Actor>
      <Actor>
        <FirstName>Ben</FirstName>
        <LastName>Shenkman (II)</LastName>
      </Actor>
      <Actor>
        <FirstName>Pamela</FirstName>
        <LastName>Hart</LastName>
      </Actor>
      <Actor>
        <FirstName>Stephen</FirstName>
        <LastName>Pearlman</LastName>
      </Actor>
      <Actor>
        <FirstName>Samia</FirstName>
        <LastName>Shoaib</LastName>
      </Actor>
      <Actor>
        <FirstName>Ajay</FirstName>
        <LastName>Naidu</LastName>
      </Actor>
      <Actor>
        <FirstName>Kristyn</FirstName>
        <LastName>Mae-Anne Lao</LastName>
      </Actor>
      <Actor>
        <FirstName>Espher</FirstName>
        <LastName>Lao Nieves</LastName>
      </Actor>
      <Actor>
        <FirstName>Joanne</FirstName>
        <LastName>Gordon</LastName>
      </Actor>
      <Actor>
        <FirstName>Lauren</FirstName>
        <LastName>Fox</LastName>
      </Actor>
      <Actor>
        <FirstName>Stanley</FirstName>
        <LastName>Herman</LastName>
      </Actor>
      <Actor>
        <FirstName>Clint</FirstName>
        <LastName>Mansell</LastName>
      </Actor>
      <Actor>
        <FirstName>Tom</FirstName>
        <LastName>Tumminello</LastName>
      </Actor>
      <Actor>
        <FirstName>Ari</FirstName>
        <LastName>Handel</LastName>
      </Actor>
    </Cast>
  </Movie>
</W4F_DOC>
